source_bing_ads/__init__.py
source_bing_ads/base_streams.py
source_bing_ads/client.py
source_bing_ads/components.py
source_bing_ads/manifest.yaml
source_bing_ads/report_streams.py
source_bing_ads/reports/__init__.py
source_bing_ads/reports/ad_performance_report.py
source_bing_ads/reports/bing_ads_reporting_service_performance_stream.py
source_bing_ads/reports/bing_ads_reporting_service_stream.py
source_bing_ads/reports/hourly_report_transformer_mixin.py
source_bing_ads/run.py
source_bing_ads/schemas/account_performance_report.json
source_bing_ads/schemas/account_performance_report_hourly.json
source_bing_ads/schemas/accounts.json
source_bing_ads/schemas/ad_performance_report.json
source_bing_ads/schemas/ad_performance_report_hourly.json
source_bing_ads/schemas/campaigns.json
source_bing_ads/schemas/product_search_query_performance_report.json
source_bing_ads/schemas/product_search_query_performance_report_hourly.json
source_bing_ads/schemas/search_query_performance_report.json
source_bing_ads/schemas/search_query_performance_report_hourly.json
source_bing_ads/source.py
source_bing_ads/spec.json
source_bing_ads/utils.py
airbyte_source_bing_ads-2.22.0.dist-info/METADATA
airbyte_source_bing_ads-2.22.0.dist-info/WHEEL
airbyte_source_bing_ads-2.22.0.dist-info/entry_points.txt
airbyte_source_bing_ads-2.22.0.dist-info/RECORD
