Metadata-Version: 2.3
Name: airbyte-source-bing-ads
Version: 2.22.0
Summary: Source implementation for Bing Ads.
License: MIT
Author: Airbyte
Author-email: contact@airbyte.io
Requires-Python: >=3.10,<3.12
Classifier: License :: OSI Approved :: MIT License
Classifier: Programming Language :: Python :: 3
Classifier: Programming Language :: Python :: 3.10
Classifier: Programming Language :: Python :: 3.11
Requires-Dist: airbyte-cdk (>=6,<7)
Requires-Dist: bingads (==13.0.18.1)
Requires-Dist: cached-property (==1.5.2)
Requires-Dist: pendulum (<3.0.0)
Requires-Dist: urllib3 (==1.26.18)
Project-URL: Documentation, https://docs.airbyte.com/integrations/sources/bing-ads
Project-URL: Homepage, https://airbyte.com
Project-URL: Repository, https://github.com/airbytehq/airbyte
